{
  "id": "nathria",
  "name": "纳斯利亚堡",
  "description": "纳斯利亚堡成就数据（来自 ifindhs wiki）",
  "updatedAt": "2026-07-20",
  "cardImageDir": "nathria",
  "referenceLinks": [
    {
      "name": "纳斯利亚堡 wiki",
      "url": "https://wiki.ifindhs.com/index.php?title=%E6%88%90%E5%B0%B1/%E6%B8%B8%E6%88%8F-%E7%BA%B3%E6%96%AF%E5%88%A9%E4%BA%9A%E5%A0%A1"
    }
  ],
  "achievements": [
    {
      "id": "nathria-001",
      "name": "花朵力量",
      "heroClass": "德鲁伊",
      "type": "一次性",
      "difficulty": "中等",
      "relatedCards": [
        "夜影花蕾"
      ],
      "recommendedDecks": [],
      "stages": [
        {
          "description": "在一局对战中使用夜影花蕾召唤一个消耗（10）点法力值的随从并施放一个消耗（10）点法力值的法术。",
          "xpReward": 0,
          "points": 20,
          "quota": 10
        }
      ]
    },
    {
      "id": "nathria-002",
      "name": "如此生动……",
      "heroClass": "德鲁伊",
      "type": "累计",
      "difficulty": "中等",
      "relatedCards": [
        "灌木巨龙托匹奥"
      ],
      "recommendedDecks": [],
      "stages": [
        {
          "description": "使用灌木巨龙托匹奥的效果召唤50条雏龙。",
          "xpReward": 0,
          "points": 10,
          "quota": 50
        },
        {
          "description": "使用灌木巨龙托匹奥的效果召唤100条雏龙。",
          "xpReward": 0,
          "points": 10,
          "quota": 100
        },
        {
          "description": "使用灌木巨龙托匹奥的效果召唤200条雏龙。",
          "xpReward": 0,
          "points": 20,
          "quota": 200
        }
      ]
    },
    {
      "id": "nathria-003",
      "name": "白骨蕾蕾",
      "heroClass": "德鲁伊",
      "type": "一次性",
      "difficulty": "中等",
      "relatedCards": [
        "树篱迷宫"
      ],
      "recommendedDecks": [],
      "stages": [
        {
          "description": "使用树篱迷宫触发75个亡语。",
          "xpReward": 0,
          "points": 20,
          "quota": 75
        }
      ]
    },
    {
      "id": "nathria-004",
      "name": "以泉谋私",
      "heroClass": "德鲁伊",
      "type": "累计",
      "difficulty": "中等",
      "relatedCards": [
        "私法程序"
      ],
      "recommendedDecks": [],
      "stages": [
        {
          "description": "使用私法程序抽100张牌。",
          "xpReward": 0,
          "points": 20,
          "quota": 100
        },
        {
          "description": "使用私法程序抽200张牌。",
          "xpReward": 0,
          "points": 20,
          "quota": 200
        }
      ]
    },
    {
      "id": "nathria-005",
      "name": "可怕骷髅",
      "heroClass": "法师",
      "type": "一次性",
      "difficulty": "中等",
      "relatedCards": [
        "不稳定的骷髅",
        "夜隐者圣所",
        "冰冷案例",
        "死神之躯",
        "天定之灾克尔苏加德"
      ],
      "recommendedDecks": [],
      "stages": [
        {
          "description": "在一局对战中触发15次不稳定的骷髅的亡语。",
          "xpReward": 0,
          "points": 20,
          "quota": 15
        }
      ]
    },
    {
      "id": "nathria-006",
      "name": "魔堡迷踪",
      "heroClass": "法师",
      "type": "一次性",
      "difficulty": "中等",
      "relatedCards": [
        "豪宅管家俄里翁"
      ],
      "recommendedDecks": [],
      "stages": [
        {
          "description": "使用豪宅管家俄里翁施放40个法师奥秘。",
          "xpReward": 0,
          "points": 20,
          "quota": 40
        }
      ]
    },
    {
      "id": "nathria-007",
      "name": "循环不畅",
      "heroClass": "法师",
      "type": "累计",
      "difficulty": "中等",
      "relatedCards": [
        "冰冻之触"
      ],
      "recommendedDecks": [],
      "stages": [
        {
          "description": "使用冰冻之触造成50点伤害。",
          "xpReward": 0,
          "points": 10,
          "quota": 50
        },
        {
          "description": "使用冰冻之触造成100点伤害。",
          "xpReward": 0,
          "points": 10,
          "quota": 100
        },
        {
          "description": "使用冰冻之触造成150点伤害。",
          "xpReward": 0,
          "points": 20,
          "quota": 150
        }
      ]
    },
    {
      "id": "nathria-008",
      "name": "驳回！",
      "heroClass": "法师",
      "type": "累计",
      "difficulty": "中等",
      "relatedCards": [
        "异议"
      ],
      "recommendedDecks": [],
      "stages": [
        {
          "description": "使用异议反制30个随从！",
          "xpReward": 0,
          "points": 20,
          "quota": 30
        },
        {
          "description": "使用异议反制60个随从！",
          "xpReward": 0,
          "points": 20,
          "quota": 60
        }
      ]
    },
    {
      "id": "nathria-009",
      "name": "猎手之友",
      "heroClass": "猎人",
      "type": "一次性",
      "difficulty": "中等",
      "relatedCards": [
        "猎手阿尔迪莫"
      ],
      "recommendedDecks": [],
      "stages": [
        {
          "description": "使用猎手阿尔迪莫一次性召唤全部三个加尔贡伙伴。",
          "xpReward": 0,
          "points": 20,
          "quota": 0
        }
      ]
    },
    {
      "id": "nathria-010",
      "name": "当心加尔贡",
      "heroClass": "猎人",
      "type": "一次性",
      "difficulty": "中等",
      "relatedCards": [
        "石缚加尔贡"
      ],
      "recommendedDecks": [],
      "stages": [
        {
          "description": "使用石缚加尔贡消灭50个随从。",
          "xpReward": 0,
          "points": 20,
          "quota": 50
        }
      ]
    },
    {
      "id": "nathria-011",
      "name": "什么？他们不是植物？",
      "heroClass": "猎人",
      "type": "累计",
      "difficulty": "中等",
      "relatedCards": [
        "灵体偷猎者",
        "野性之魂",
        "雄鹿冲锋",
        "艾拉隆"
      ],
      "recommendedDecks": [],
      "stages": [
        {
          "description": "召唤100个休眠的灵种。",
          "xpReward": 0,
          "points": 10,
          "quota": 100
        },
        {
          "description": "召唤200个休眠的灵种。",
          "xpReward": 0,
          "points": 10,
          "quota": 200
        },
        {
          "description": "召唤300个休眠的灵种。",
          "xpReward": 0,
          "points": 20,
          "quota": 300
        }
      ]
    },
    {
      "id": "nathria-012",
      "name": "藐视公堂",
      "heroClass": "猎人",
      "type": "累计",
      "difficulty": "中等",
      "relatedCards": [
        "否决动议"
      ],
      "recommendedDecks": [],
      "stages": [
        {
          "description": "用否决动议消灭敌方英雄。",
          "xpReward": 0,
          "points": 20,
          "quota": 0
        },
        {
          "description": "用否决动议消灭敌方英雄，完成3次。",
          "xpReward": 0,
          "points": 20,
          "quota": 3
        }
      ]
    },
    {
      "id": "nathria-013",
      "name": "我就是强化版的你",
      "heroClass": "牧师",
      "type": "一次性",
      "difficulty": "中等",
      "relatedCards": [
        "盗用身份"
      ],
      "recommendedDecks": [],
      "stages": [
        {
          "description": "使用盗用身份发现一个对手的英雄牌的1张复制。",
          "xpReward": 0,
          "points": 20,
          "quota": 1
        }
      ]
    },
    {
      "id": "nathria-014",
      "name": "错失看点",
      "heroClass": "牧师",
      "type": "一次性",
      "difficulty": "中等",
      "relatedCards": [
        "净场"
      ],
      "recommendedDecks": [],
      "stages": [
        {
          "description": "使用净场消灭75个随从。",
          "xpReward": 0,
          "points": 20,
          "quota": 75
        }
      ]
    },
    {
      "id": "nathria-015",
      "name": "SPF值300",
      "heroClass": "牧师",
      "type": "累计",
      "difficulty": "中等",
      "relatedCards": [
        "炽燃圣光"
      ],
      "recommendedDecks": [],
      "stages": [
        {
          "description": "使用炽燃圣光造成100点伤害。",
          "xpReward": 0,
          "points": 10,
          "quota": 100
        },
        {
          "description": "使用炽燃圣光造成200点伤害。",
          "xpReward": 0,
          "points": 10,
          "quota": 200
        },
        {
          "description": "使用炽燃圣光造成300点伤害。",
          "xpReward": 0,
          "points": 20,
          "quota": 300
        }
      ]
    },
    {
      "id": "nathria-016",
      "name": "严重盗窃",
      "heroClass": "牧师",
      "type": "累计",
      "difficulty": "中等",
      "relatedCards": [
        "控罪心灵密探"
      ],
      "recommendedDecks": [],
      "stages": [
        {
          "description": "使用控罪心灵密探将你对手的卡牌的20张复制置入你的手牌。",
          "xpReward": 0,
          "points": 20,
          "quota": 20
        },
        {
          "description": "使用控罪心灵密探将你对手的卡牌的40张复制置入你的手牌。",
          "xpReward": 0,
          "points": 20,
          "quota": 40
        }
      ]
    },
    {
      "id": "nathria-017",
      "name": "你说这是把剑？",
      "heroClass": "潜行者",
      "type": "一次性",
      "difficulty": "中等",
      "relatedCards": [
        "通灵领主德拉卡"
      ],
      "recommendedDecks": [],
      "stages": [
        {
          "description": "用通灵领主德拉卡装备一把攻击力为10的匕首。",
          "xpReward": 0,
          "points": 20,
          "quota": 10
        }
      ]
    },
    {
      "id": "nathria-018",
      "name": "*闷声惊叫*",
      "heroClass": "潜行者",
      "type": "一次性",
      "difficulty": "中等",
      "relatedCards": [
        "绑架"
      ],
      "recommendedDecks": [],
      "stages": [
        {
          "description": "绑架50个随从。",
          "xpReward": 0,
          "points": 20,
          "quota": 50
        }
      ]
    },
    {
      "id": "nathria-019",
      "name": "地穴传说",
      "heroClass": "潜行者",
      "type": "累计",
      "difficulty": "中等",
      "relatedCards": [
        "罪碑坟场"
      ],
      "recommendedDecks": [],
      "stages": [
        {
          "description": "使用罪碑坟场召唤50个幽灵。",
          "xpReward": 0,
          "points": 10,
          "quota": 50
        },
        {
          "description": "使用罪碑坟场召唤100个幽灵。",
          "xpReward": 0,
          "points": 10,
          "quota": 100
        },
        {
          "description": "使用罪碑坟场召唤150个幽灵。",
          "xpReward": 0,
          "points": 20,
          "quota": 150
        }
      ]
    },
    {
      "id": "nathria-020",
      "name": "全部真相？！",
      "heroClass": "潜行者",
      "type": "累计",
      "difficulty": "中等",
      "relatedCards": [
        "伪证"
      ],
      "recommendedDecks": [],
      "stages": [
        {
          "description": "使用伪证施放25个奥秘。",
          "xpReward": 0,
          "points": 20,
          "quota": 25
        },
        {
          "description": "使用伪证施放50个奥秘。",
          "xpReward": 0,
          "points": 20,
          "quota": 50
        }
      ]
    },
    {
      "id": "nathria-021",
      "name": "林中的图腾倒下了……",
      "heroClass": "萨满祭司",
      "type": "一次性",
      "difficulty": "中等",
      "relatedCards": [],
      "recommendedDecks": [],
      "stages": [
        {
          "description": "控制满场的图腾。",
          "xpReward": 0,
          "points": 20,
          "quota": 0
        }
      ]
    },
    {
      "id": "nathria-022",
      "name": "原始汤剂",
      "heroClass": "萨满祭司",
      "type": "一次性",
      "difficulty": "中等",
      "relatedCards": [
        "瓦丝琪女男爵"
      ],
      "recommendedDecks": [],
      "stages": [
        {
          "description": "使用瓦丝琪女男爵的效果召唤40个随从。",
          "xpReward": 0,
          "points": 20,
          "quota": 40
        }
      ]
    },
    {
      "id": "nathria-023",
      "name": "逃离泥渊",
      "heroClass": "萨满祭司",
      "type": "累计",
      "difficulty": "中等",
      "relatedCards": [
        "淤泥之池"
      ],
      "recommendedDecks": [],
      "stages": [
        {
          "description": "使用淤泥之池变形50个友方随从。",
          "xpReward": 0,
          "points": 10,
          "quota": 50
        },
        {
          "description": "使用淤泥之池变形100个友方随从。",
          "xpReward": 0,
          "points": 10,
          "quota": 100
        },
        {
          "description": "使用淤泥之池变形150个友方随从。",
          "xpReward": 0,
          "points": 20,
          "quota": 150
        }
      ]
    },
    {
      "id": "nathria-024",
      "name": "替朋友留的",
      "heroClass": "萨满祭司",
      "type": "累计",
      "difficulty": "中等",
      "relatedCards": [
        "栽赃者"
      ],
      "recommendedDecks": [],
      "stages": [
        {
          "description": "使用栽赃者使你的对手过载20个法力水晶。",
          "xpReward": 0,
          "points": 20,
          "quota": 20
        },
        {
          "description": "使用栽赃者使你的对手过载40个法力水晶。",
          "xpReward": 0,
          "points": 20,
          "quota": 40
        }
      ]
    },
    {
      "id": "nathria-025",
      "name": "重磅嘉宾",
      "heroClass": "圣骑士",
      "type": "一次性",
      "difficulty": "中等",
      "relatedCards": [
        "女伯爵"
      ],
      "recommendedDecks": [],
      "stages": [
        {
          "description": "使用传说邀请函邀请16个不同的传说随从。",
          "xpReward": 0,
          "points": 20,
          "quota": 16
        }
      ]
    },
    {
      "id": "nathria-026",
      "name": "火速晋升",
      "heroClass": "圣骑士",
      "type": "一次性",
      "difficulty": "中等",
      "relatedCards": [
        "晋升"
      ],
      "recommendedDecks": [],
      "stages": [
        {
          "description": "使用晋升将一个白银之手新兵晋升至10点或以上的攻击力。",
          "xpReward": 0,
          "points": 20,
          "quota": 10
        }
      ]
    },
    {
      "id": "nathria-027",
      "name": "圣钟为谁而鸣",
      "heroClass": "圣骑士",
      "type": "累计",
      "difficulty": "中等",
      "relatedCards": [
        "圣洁鸣钟"
      ],
      "recommendedDecks": [],
      "stages": [
        {
          "description": "使用圣洁鸣钟造成30点伤害。",
          "xpReward": 0,
          "points": 10,
          "quota": 30
        },
        {
          "description": "使用圣洁鸣钟造成60点伤害。",
          "xpReward": 0,
          "points": 10,
          "quota": 60
        },
        {
          "description": "使用圣洁鸣钟造成120点伤害。",
          "xpReward": 0,
          "points": 20,
          "quota": 120
        }
      ]
    },
    {
      "id": "nathria-028",
      "name": "有权索赔",
      "heroClass": "圣骑士",
      "type": "累计",
      "difficulty": "中等",
      "relatedCards": [
        "集体诉讼律师"
      ],
      "recommendedDecks": [],
      "stages": [
        {
          "description": "使用集体诉讼律师将25个随从的属性值变为1/1。",
          "xpReward": 0,
          "points": 20,
          "quota": 25
        },
        {
          "description": "使用集体诉讼律师将50个随从的属性值变为1/1。",
          "xpReward": 0,
          "points": 20,
          "quota": 50
        }
      ]
    },
    {
      "id": "nathria-029",
      "name": "双人成舞",
      "heroClass": "术士",
      "type": "一次性",
      "difficulty": "中等",
      "relatedCards": [
        "暗影华尔兹"
      ],
      "recommendedDecks": [],
      "stages": [
        {
          "description": "使用暗影华尔兹召唤50个影子。",
          "xpReward": 0,
          "points": 20,
          "quota": 50
        }
      ]
    },
    {
      "id": "nathria-030",
      "name": "鬼神之援",
      "heroClass": "术士",
      "type": "一次性",
      "difficulty": "中等",
      "relatedCards": [
        "灾祸降临"
      ],
      "recommendedDecks": [],
      "stages": [
        {
          "description": "使用一张灾祸降临抽7张牌。",
          "xpReward": 0,
          "points": 20,
          "quota": 7
        }
      ]
    },
    {
      "id": "nathria-031",
      "name": "鬼神壮举",
      "heroClass": "术士",
      "type": "累计",
      "difficulty": "中等",
      "relatedCards": [
        "小鬼大王拉法姆"
      ],
      "recommendedDecks": [],
      "stages": [
        {
          "description": "使用小鬼大王拉法姆召唤60个小鬼。",
          "xpReward": 0,
          "points": 10,
          "quota": 60
        },
        {
          "description": "使用小鬼大王拉法姆召唤120个小鬼。",
          "xpReward": 0,
          "points": 10,
          "quota": 120
        },
        {
          "description": "使用小鬼大王拉法姆召唤200个小鬼。",
          "xpReward": 0,
          "points": 20,
          "quota": 200
        }
      ]
    },
    {
      "id": "nathria-032",
      "name": "尸横当场",
      "heroClass": "术士",
      "type": "累计",
      "difficulty": "中等",
      "relatedCards": [
        "尸身保护令"
      ],
      "recommendedDecks": [],
      "stages": [
        {
          "description": "使用尸身保护令召唤3个传说随从。",
          "xpReward": 0,
          "points": 20,
          "quota": 3
        },
        {
          "description": "使用尸身保护令召唤5个传说随从。",
          "xpReward": 0,
          "points": 20,
          "quota": 5
        }
      ]
    },
    {
      "id": "nathria-033",
      "name": "敏锐发现",
      "heroClass": "恶魔猎手",
      "type": "一次性",
      "difficulty": "中等",
      "relatedCards": [
        "放大战刃"
      ],
      "recommendedDecks": [],
      "stages": [
        {
          "description": "使用放大战刃抽30张牌。",
          "xpReward": 0,
          "points": 20,
          "quota": 30
        }
      ]
    },
    {
      "id": "nathria-034",
      "name": "破坏成性",
      "heroClass": "恶魔猎手",
      "type": "一次性",
      "difficulty": "中等",
      "relatedCards": [
        "贪食的克里克西斯"
      ],
      "recommendedDecks": [],
      "stages": [
        {
          "description": "使用一张贪食的克里克西斯弃掉8张牌。",
          "xpReward": 0,
          "points": 20,
          "quota": 8
        }
      ]
    },
    {
      "id": "nathria-035",
      "name": "这东西应该藏在博物馆里！",
      "heroClass": "恶魔猎手",
      "type": "累计",
      "difficulty": "中等",
      "relatedCards": [
        "灭绝圣物",
        "幻灭心能圣物",
        "次元圣物"
      ],
      "recommendedDecks": [],
      "stages": [
        {
          "description": "施放25个圣物。",
          "xpReward": 0,
          "points": 10,
          "quota": 25
        },
        {
          "description": "施放50个圣物。",
          "xpReward": 0,
          "points": 10,
          "quota": 50
        },
        {
          "description": "施放100个圣物。",
          "xpReward": 0,
          "points": 20,
          "quota": 100
        }
      ]
    },
    {
      "id": "nathria-036",
      "name": "恶魔代言人",
      "heroClass": "恶魔猎手",
      "type": "累计",
      "difficulty": "中等",
      "relatedCards": [
        "邪能之乱"
      ],
      "recommendedDecks": [],
      "stages": [
        {
          "description": "使用邪能之乱召唤25个恶魔。",
          "xpReward": 0,
          "points": 20,
          "quota": 25
        },
        {
          "description": "使用邪能之乱召唤50个恶魔。",
          "xpReward": 0,
          "points": 20,
          "quota": 50
        }
      ]
    },
    {
      "id": "nathria-037",
      "name": "罪恶之城",
      "heroClass": "战士",
      "type": "一次性",
      "difficulty": "中等",
      "relatedCards": [
        "心能提取者"
      ],
      "recommendedDecks": [],
      "stages": [
        {
          "description": "使用一张心能提取者使随从获得+7/+7。",
          "xpReward": 0,
          "points": 20,
          "quota": 7
        }
      ]
    },
    {
      "id": "nathria-038",
      "name": "我来，我见，我征服",
      "heroClass": "战士",
      "type": "一次性",
      "difficulty": "中等",
      "relatedCards": [
        "征服者战旗"
      ],
      "recommendedDecks": [],
      "stages": [
        {
          "description": "使用征服者战旗抽50张牌。",
          "xpReward": 0,
          "points": 20,
          "quota": 50
        }
      ]
    },
    {
      "id": "nathria-039",
      "name": "活死刃之夜",
      "heroClass": "战士",
      "type": "累计",
      "difficulty": "中等",
      "relatedCards": [
        "活体利刃蕾茉妮雅"
      ],
      "recommendedDecks": [],
      "stages": [
        {
          "description": "使用活体利刃蕾茉妮雅造成50点伤害。",
          "xpReward": 0,
          "points": 10,
          "quota": 50
        },
        {
          "description": "使用活体利刃蕾茉妮雅造成100点伤害。",
          "xpReward": 0,
          "points": 10,
          "quota": 100
        },
        {
          "description": "使用活体利刃蕾茉妮雅造成200点伤害。",
          "xpReward": 0,
          "points": 20,
          "quota": 200
        }
      ]
    },
    {
      "id": "nathria-040",
      "name": "证人灭口流程",
      "heroClass": "战士",
      "type": "累计",
      "difficulty": "中等",
      "relatedCards": [
        "传唤出庭"
      ],
      "recommendedDecks": [],
      "stages": [
        {
          "description": "使用传唤出庭召唤随从并在同一回合将其消灭，完成15次。",
          "xpReward": 0,
          "points": 20,
          "quota": 15
        },
        {
          "description": "使用传唤出庭召唤随从并在同一回合将其消灭，完成30次。",
          "xpReward": 0,
          "points": 20,
          "quota": 30
        }
      ]
    },
    {
      "id": "nathria-041",
      "name": "老无所依的布兰契",
      "heroClass": "中立",
      "type": "累计",
      "difficulty": "中等",
      "relatedCards": [
        "罪奔者"
      ],
      "recommendedDecks": [],
      "stages": [
        {
          "description": "使用罪奔者消灭20个随从。",
          "xpReward": 0,
          "points": 10,
          "quota": 20
        },
        {
          "description": "使用罪奔者消灭40个随从。",
          "xpReward": 0,
          "points": 10,
          "quota": 40
        },
        {
          "description": "使用罪奔者消灭80个随从。",
          "xpReward": 0,
          "points": 20,
          "quota": 80
        }
      ]
    },
    {
      "id": "nathria-042",
      "name": "注意地标",
      "heroClass": "中立",
      "type": "累计",
      "difficulty": "中等",
      "relatedCards": [],
      "recommendedDecks": [],
      "stages": [
        {
          "description": "激活地标60次。",
          "xpReward": 0,
          "points": 10,
          "quota": 60
        },
        {
          "description": "激活地标120次。",
          "xpReward": 0,
          "points": 10,
          "quota": 120
        },
        {
          "description": "激活地标200次。",
          "xpReward": 0,
          "points": 20,
          "quota": 200
        }
      ]
    },
    {
      "id": "nathria-043",
      "name": "七宗死罪",
      "heroClass": "中立",
      "type": "累计",
      "difficulty": "中等",
      "relatedCards": [],
      "recommendedDecks": [],
      "stages": [
        {
          "description": "使用50张已注能的牌。",
          "xpReward": 0,
          "points": 10,
          "quota": 50
        },
        {
          "description": "使用100张已注能的牌。",
          "xpReward": 0,
          "points": 10,
          "quota": 100
        },
        {
          "description": "使用200张已注能的牌。",
          "xpReward": 0,
          "points": 20,
          "quota": 200
        }
      ]
    },
    {
      "id": "nathria-044",
      "name": "住手！这是注能时间！",
      "heroClass": "中立",
      "type": "累计",
      "difficulty": "中等",
      "relatedCards": [
        "饥饿的愚人"
      ],
      "recommendedDecks": [],
      "stages": [
        {
          "description": "使用饥饿的愚人抽45张牌。",
          "xpReward": 0,
          "points": 10,
          "quota": 45
        },
        {
          "description": "使用饥饿的愚人抽90张牌。",
          "xpReward": 0,
          "points": 20,
          "quota": 90
        }
      ]
    },
    {
      "id": "nathria-045",
      "name": "全能武装",
      "heroClass": "中立",
      "type": "一次性",
      "difficulty": "中等",
      "relatedCards": [
        "罪能魔像"
      ],
      "recommendedDecks": [],
      "stages": [
        {
          "description": "在你的回合结束时，拥有一个攻击力大于或等于20点的罪能魔像。",
          "xpReward": 0,
          "points": 20,
          "quota": 20
        }
      ]
    },
    {
      "id": "nathria-046",
      "name": "噩耗使者",
      "heroClass": "中立",
      "type": "累计",
      "difficulty": "中等",
      "relatedCards": [
        "晚宴表演者"
      ],
      "recommendedDecks": [],
      "stages": [
        {
          "description": "使用晚宴表演者召唤8个不同的随从。",
          "xpReward": 0,
          "points": 20,
          "quota": 8
        },
        {
          "description": "使用晚宴表演者召唤16个不同的随从。",
          "xpReward": 0,
          "points": 20,
          "quota": 16
        }
      ]
    },
    {
      "id": "nathria-047",
      "name": "喂他们吃漏斗蛋糕！",
      "heroClass": "中立",
      "type": "一次性",
      "difficulty": "中等",
      "relatedCards": [
        "癫狂公爵西塔尔"
      ],
      "recommendedDecks": [],
      "stages": [
        {
          "description": "使用癫狂公爵西塔尔交换一张普通牌和一张传说牌。",
          "xpReward": 0,
          "points": 20,
          "quota": 0
        }
      ]
    },
    {
      "id": "nathria-048",
      "name": "干洗服务",
      "heroClass": "中立",
      "type": "一次性",
      "difficulty": "中等",
      "relatedCards": [
        "蒸汽清洁器"
      ],
      "recommendedDecks": [],
      "stages": [
        {
          "description": "使用蒸汽清洁器摧毁30张牌。",
          "xpReward": 0,
          "points": 20,
          "quota": 30
        }
      ]
    },
    {
      "id": "nathria-049",
      "name": "吾王万岁",
      "heroClass": "中立",
      "type": "累计",
      "difficulty": "中等",
      "relatedCards": [
        "德纳修斯大帝"
      ],
      "recommendedDecks": [],
      "stages": [
        {
          "description": "使用德纳修斯大帝造成200点伤害。",
          "xpReward": 0,
          "points": 10,
          "quota": 200
        },
        {
          "description": "使用德纳修斯大帝造成400点伤害。",
          "xpReward": 0,
          "points": 10,
          "quota": 400
        },
        {
          "description": "使用德纳修斯大帝造成600点伤害。",
          "xpReward": 0,
          "points": 20,
          "quota": 600
        }
      ]
    },
    {
      "id": "nathria-050",
      "name": "模仿游戏",
      "heroClass": "中立",
      "type": "一次性",
      "difficulty": "中等",
      "relatedCards": [
        "诡异的画像"
      ],
      "recommendedDecks": [],
      "stages": [
        {
          "description": "将诡异的画像变形成为10个不同职业的随从。",
          "xpReward": 0,
          "points": 20,
          "quota": 10
        }
      ]
    },
    {
      "id": "nathria-051",
      "name": "早餐十六顿",
      "heroClass": "中立",
      "type": "一次性",
      "difficulty": "中等",
      "relatedCards": [
        "贪食的吞噬者"
      ],
      "recommendedDecks": [],
      "stages": [
        {
          "description": "使用贪食的吞噬者的效果吞食25个随从。",
          "xpReward": 0,
          "points": 20,
          "quota": 25
        }
      ]
    },
    {
      "id": "nathria-052",
      "name": "经典失误之一",
      "heroClass": "中立",
      "type": "一次性",
      "difficulty": "中等",
      "relatedCards": [
        "可疑的炼金师",
        "可疑的海盗",
        "可疑的侍应"
      ],
      "recommendedDecks": [],
      "stages": [
        {
          "description": "使用可疑的炼金师，可疑的海盗和可疑的侍应愚弄你的对手。",
          "xpReward": 0,
          "points": 20,
          "quota": 0
        }
      ]
    },
    {
      "id": "nathria-053",
      "name": "这是基本元素，亲爱的华生",
      "heroClass": "中立",
      "type": "一次性",
      "difficulty": "中等",
      "relatedCards": [
        "摩洛克·福尔摩斯"
      ],
      "recommendedDecks": [],
      "stages": [
        {
          "description": "使用摩洛克·福尔摩斯完全猜中你对手的三张牌。",
          "xpReward": 0,
          "points": 20,
          "quota": 0
        }
      ]
    },
    {
      "id": "nathria-054",
      "name": "她什么都没做错",
      "heroClass": "中立",
      "type": "累计",
      "difficulty": "中等",
      "relatedCards": [
        "被告希尔瓦娜斯"
      ],
      "recommendedDecks": [],
      "stages": [
        {
          "description": "使用被告希尔瓦娜斯获取10个随从的控制权。",
          "xpReward": 0,
          "points": 20,
          "quota": 10
        },
        {
          "description": "使用被告希尔瓦娜斯获取20个随从的控制权。",
          "xpReward": 0,
          "points": 20,
          "quota": 20
        }
      ]
    },
    {
      "id": "nathria-055",
      "name": "离魂难忘",
      "heroClass": "中立",
      "type": "一次性",
      "difficulty": "中等",
      "relatedCards": [
        "离躯之魂"
      ],
      "recommendedDecks": [],
      "stages": [
        {
          "description": "使用离躯之魂从你的牌库中发现30张牌。",
          "xpReward": 0,
          "points": 20,
          "quota": 30
        }
      ]
    },
    {
      "id": "nathria-056",
      "name": "需要地图吗？",
      "heroClass": "中立",
      "type": "一次性",
      "difficulty": "中等",
      "relatedCards": [
        "迷宫向导"
      ],
      "recommendedDecks": [],
      "stages": [
        {
          "description": "使用迷宫向导召唤30个随从。",
          "xpReward": 0,
          "points": 20,
          "quota": 30
        }
      ]
    },
    {
      "id": "nathria-057",
      "name": "顽石军团，集合！",
      "heroClass": "中立",
      "type": "一次性",
      "difficulty": "中等",
      "relatedCards": [
        "石裔干将"
      ],
      "recommendedDecks": [],
      "stages": [
        {
          "description": "使用石裔干将造成160点伤害。",
          "xpReward": 0,
          "points": 20,
          "quota": 160
        }
      ]
    },
    {
      "id": "nathria-058",
      "name": "？？？",
      "heroClass": "中立",
      "type": "一次性",
      "difficulty": "中等",
      "relatedCards": [],
      "recommendedDecks": [],
      "stages": [
        {
          "description": "解开埋藏在纳斯利亚堡的谜题。",
          "xpReward": 0,
          "points": 100,
          "quota": 0
        }
      ]
    },
    {
      "id": "nathria-059",
      "name": "我算是好牌吗？",
      "heroClass": "中立",
      "type": "累计",
      "difficulty": "中等",
      "relatedCards": [
        "冥界侍从"
      ],
      "recommendedDecks": [],
      "stages": [
        {
          "description": "当冥界侍从在场时，25个友方随从死亡。",
          "xpReward": 0,
          "points": 10,
          "quota": 25
        },
        {
          "description": "当冥界侍从在场时，50个友方随从死亡。",
          "xpReward": 0,
          "points": 10,
          "quota": 50
        }
      ]
    }
  ]
}
